setup.cfg
setup.py
bookshelf/__init__.py
bookshelf/__main__.py
bookshelf/api_v1.py
bookshelf/api_v2/__init__.py
bookshelf/api_v2/cloud.py
bookshelf/api_v2/debug.py
bookshelf/api_v2/docker.py
bookshelf/api_v2/ec2.py
bookshelf/api_v2/file.py
bookshelf/api_v2/git.py
bookshelf/api_v2/java.py
bookshelf/api_v2/logging_helpers.py
bookshelf/api_v2/os_helpers.py
bookshelf/api_v2/pkg.py
bookshelf/api_v2/python.py
bookshelf/api_v2/rackspace.py
bookshelf/api_v2/time_helpers.py
bookshelf/api_v2/vagrant.py
bookshelf/api_v3/__init__.py
bookshelf/api_v3/cloud_instance.py
bookshelf/api_v3/ec2.py
bookshelf/api_v3/gce.py
bookshelf/api_v3/rackspace.py
bookshelf/tests/__init__.py
bookshelf/tests/api_v2/__init__.py
bookshelf/tests/api_v2/docker_based_tests.py
bookshelf/tests/api_v2/test_docker.py
bookshelf/tests/api_v2/test_ec2.py
bookshelf/tests/api_v2/test_file.py
bookshelf/tests/api_v2/test_git.py
bookshelf/tests/api_v2/test_java.py
bookshelf/tests/api_v2/test_os.py
bookshelf/tests/api_v2/test_pkg.py
bookshelf/tests/api_v2/test_python.py
bookshelf/tests/api_v2/test_rackspace.py
bookshelf/tests/api_v2/test_vagrant.py
bookshelf/tests/api_v2/vagrant_based_tests.py
bookshelf/tests/api_v3/__init__.py
bookshelf/tests/api_v3/test_cloud.py
bookshelf/tests/api_v3/test_interfaces.py
pyBookshelf.egg-info/PKG-INFO
pyBookshelf.egg-info/SOURCES.txt
pyBookshelf.egg-info/dependency_links.txt
pyBookshelf.egg-info/requires.txt
pyBookshelf.egg-info/top_level.txt