Metadata-Version: 1.0
Name: pyBookshelf
Version: 3.0.1
Summary: Bookshelf of Fabric functions
Home-page: https://www.github.com/pyBookshelf/Bookshelf/
Author: Jorge Costa
Author-email: pybookshelf@azulinho.com
License: GPL v3
Platform: UNKNOWN
